<?xml version='1.0' encoding='UTF-8'?>
<traffic_config><ethernet_layer><frame_size>512</frame_size><mac_dst>00:00:01:00:00:01</mac_dst><l2_encap>ethernet_ii</l2_encap><mac_src>00:10:94:00:00:02</mac_src></ethernet_layer><ip_layer><l3_protocol>ipv6</l3_protocol><ipv6_flow_label>0</ipv6_flow_label><ipv6_traffic_class>0</ipv6_traffic_class><ipv6_dst_addr>2000::CA01:0001</ipv6_dst_addr><ipv6_hop_limit>255</ipv6_hop_limit><l3_length>494</l3_length><ipv6_length>0</ipv6_length><ipv6_src_addr>2000::AC01:0001</ipv6_src_addr><ipv6_next_header>6</ipv6_next_header></ip_layer><tcp_layer><tcp_checksum>0</tcp_checksum><tcp_ack_flag>1</tcp_ack_flag><tcp_data_offset>5</tcp_data_offset><tcp_urgent_ptr>0</tcp_urgent_ptr><tcp_src_port>1</tcp_src_port><tcp_rst_flag>0</tcp_rst_flag><tcp_fin_flag>0</tcp_fin_flag><tcp_urg_flag>0</tcp_urg_flag><tcp_window>4096</tcp_window><tcp_dst_port>25001</tcp_dst_port><l4_protocol>tcp</l4_protocol><tcp_reserved>0</tcp_reserved><tcp_seq_num>123456</tcp_seq_num><tcp_ack_num>234567</tcp_ack_num><tcp_psh_flag>0</tcp_psh_flag><tcp_syn_flag>0</tcp_syn_flag></tcp_layer><stc_layer><fill_value>0</fill_value><disable_signature>0</disable_signature></stc_layer><stream><tcp_dst_port_count>5001</tcp_dst_port_count><tcp_dst_port_step>1</tcp_dst_port_step><tcp_dst_port_repeat_count>0</tcp_dst_port_repeat_count><tcp_dst_port_mode>increment</tcp_dst_port_mode><tcp_src_port_repeat_count>0</tcp_src_port_repeat_count><tcp_src_port_count>5001</tcp_src_port_count><tcp_src_port_mode>increment</tcp_src_port_mode><name>F-IPv6-L-0-1</name><tcp_src_port_step>1</tcp_src_port_step></stream><other><traffic_state>1</traffic_state><tx_port_sending_traffic_to_self_en>false</tx_port_sending_traffic_to_self_en><ipv6_srcprefix>::FFFF:FFFF</ipv6_srcprefix><pkts_per_burst>1</pkts_per_burst><high_speed_result_analysis>1</high_speed_result_analysis><enable_stream_only_gen>1</enable_stream_only_gen><inter_stream_gap_unit>bytes</inter_stream_gap_unit><fill_type>constant</fill_type><length_mode>fixed</length_mode><port_handle>port_handle[0]</port_handle><ipv6_src_repeat_count>0</ipv6_src_repeat_count><ipv6_src_mode>increment</ipv6_src_mode><rate_pps>10000</rate_pps><mode>create</mode><burst_loop_count>burst_loop_count</burst_loop_count><enable_control_plane>0</enable_control_plane><ipv6_src_step>::1</ipv6_src_step><ipv6_src_count>200</ipv6_src_count><mac_discovery_gw>::0</mac_discovery_gw><inter_stream_gap>12</inter_stream_gap><enable_stream>false</enable_stream><ipv6_srcprefix_len>12</ipv6_srcprefix_len><fcs_error>0</fcs_error></other></traffic_config>